image_enhancement/__init__.py
image_enhancement/histogram.py
image_enhancement/image_enhancement.py
image_enhancement/quantitation.py
image_enhancement/utils.py
image_enhancement-0.2.0.dist-info/LICENSE
image_enhancement-0.2.0.dist-info/METADATA
image_enhancement-0.2.0.dist-info/WHEEL
image_enhancement-0.2.0.dist-info/top_level.txt
image_enhancement-0.2.0.dist-info/RECORD
