Metadata-Version: 2.1
Name: image-enhancement
Version: 0.2.0
Summary: 🌈 Library to enhance image
Home-page: https://github.com/Nguyen-Hoang-Nam/image-enhancement
Author: Nguyen Hoang Nam
Author-email: nguyenhoangnam.dev@gmail.com
License: MIT
Platform: UNKNOWN
Requires-Dist: numpy
Requires-Dist: opencv-python
